omfiles-1.1.0.dist-info/METADATA
omfiles-1.1.0.dist-info/WHEEL
omfiles-1.1.0.dist-info/entry_points.txt
omfiles-1.1.0.dist-info/licenses/LICENSE
omfiles.libs/libgcc_s-6d2d9dc8.so.1
omfiles/__init__.py
omfiles/_numcodecs.py
omfiles/_zarr3.py
omfiles/chunk_reader.py
omfiles/grids/__init__.py
omfiles/grids/gaussian.py
omfiles/grids/om_grid.py
omfiles/grids/regular.py
omfiles/meta.py
omfiles/omfiles.abi3.so
omfiles/omfiles.pyi
omfiles/py.typed
omfiles/types.py
omfiles/xarray.py
omfiles-1.1.0.dist-info/RECORD
