Metadata-Version: 2.4
Name: omfiles
Version: 1.1.0
Classifier: Programming Language :: Rust
Classifier: Programming Language :: Python :: Implementation :: CPython
Classifier: Programming Language :: Python :: Implementation :: PyPy
Requires-Dist: numpy>=1.21.0
Requires-Dist: zarr>=2.18.2 ; extra == 'codec'
Requires-Dist: numcodecs>=0.12.1 ; extra == 'codec'
Requires-Dist: xarray>=2023.1.0 ; extra == 'xarray'
Requires-Dist: fsspec>=2023.1.0 ; extra == 'fsspec'
Requires-Dist: s3fs>=2023.1.0 ; extra == 'fsspec'
Requires-Dist: pyproj>=3.1.0 ; extra == 'grids'
Requires-Dist: zarr>=2.18.2 ; extra == 'all'
Requires-Dist: numcodecs>=0.12.1 ; extra == 'all'
Requires-Dist: xarray>=2023.1.0 ; extra == 'all'
Requires-Dist: fsspec>=2023.10.0 ; extra == 'all'
Requires-Dist: s3fs>=2023.1.0 ; extra == 'all'
Requires-Dist: pyproj>=3.1.0 ; extra == 'all'
Provides-Extra: codec
Provides-Extra: xarray
Provides-Extra: fsspec
Provides-Extra: grids
Provides-Extra: all
License-File: LICENSE
Summary: Python bindings for the Open-Meteo file format
Author-email: Terraputix <terraputix@mailbox.org>
Maintainer-email: Terraputix <terraputix@mailbox.org>
License-Expression: GPL-2.0-only
Requires-Python: >=3.9
Project-URL: Homepage, https://github.com/open-meteo/python-omfiles
Project-URL: Documentation, https://open-meteo.github.io/python-omfiles/
Project-URL: Source, https://github.com/open-meteo/python-omfiles
Project-URL: Tracker, https://github.com/open-meteo/python-omfiles/issues
